score/__init__.py
score/cli.py
score/config.py
score/find_score.py
score/findscore.py
score/score.py
score/configs/__init__.py
score/configs/config.py
tests/__init__.py
tests/test_config.py
tests/test_findscore.py
imagescore-1.0.4.dist-info/LICENSE.txt
imagescore-1.0.4.dist-info/METADATA
imagescore-1.0.4.dist-info/WHEEL
imagescore-1.0.4.dist-info/entry_points.txt
imagescore-1.0.4.dist-info/top_level.txt
imagescore-1.0.4.dist-info/RECORD
