Metadata-Version: 2.1
Name: imagescore
Version: 1.0.4
Summary: Calculates the similarity score between images
Home-page: https://github.com/sandjaie/image_score
Author: sandjaie
Author-email: sandjaie@gmail.com
License: MIT
Download-URL: https://github.com/sandjaie/image_score/archive/1.0.4.tar.gz
Platform: UNKNOWN
Classifier: License :: OSI Approved :: MIT License
Classifier: Operating System :: OS Independent
Classifier: Environment :: Console
Classifier: Programming Language :: Python
Classifier: Programming Language :: Python :: 3.7
Requires-Dist: opencv-python
Requires-Dist: scikit-image
Requires-Dist: click
